minimagen/Imagen.py
minimagen/Unet.py
minimagen/__init__.py
minimagen/diffusion_model.py
minimagen/generate.py
minimagen/helpers.py
minimagen/layers.py
minimagen/t5.py
minimagen/training.py
minimagen-0.0.9.dist-info/LICENSE
minimagen-0.0.9.dist-info/METADATA
minimagen-0.0.9.dist-info/WHEEL
minimagen-0.0.9.dist-info/top_level.txt
minimagen-0.0.9.dist-info/RECORD
