Metadata-Version: 2.1
Name: minimagen
Version: 0.0.9
Summary: Minimal Imagen text-to-image model implementation.
Home-page: UNKNOWN
Author: AssemblyAI
Author-email: <ryan@assemblyai.com>
License: UNKNOWN
Keywords: imagen,text-to-image,diffusion model,super resolution,image generation,machine learning,deep learning,pytorch,python
Platform: UNKNOWN
Classifier: Intended Audience :: Developers
Classifier: Programming Language :: Python :: 3
Classifier: Operating System :: Unix
Classifier: Operating System :: MacOS :: MacOS X
Classifier: Operating System :: Microsoft :: Windows
License-File: LICENSE
Requires-Dist: aiohttp (==3.8.1)
Requires-Dist: aiosignal (==1.2.0)
Requires-Dist: async-timeout (==4.0.2)
Requires-Dist: attrs (==21.4.0)
Requires-Dist: certifi (==2022.6.15)
Requires-Dist: charset-normalizer (==2.1.0)
Requires-Dist: colorama (==0.4.5)
Requires-Dist: datasets (==2.3.2)
Requires-Dist: dill (==0.3.5.1)
Requires-Dist: einops (==0.4.1)
Requires-Dist: einops-exts (==0.0.3)
Requires-Dist: filelock (==3.7.1)
Requires-Dist: frozenlist (==1.3.0)
Requires-Dist: fsspec (==2022.5.0)
Requires-Dist: future (==0.18.2)
Requires-Dist: huggingface-hub (==0.8.1)
Requires-Dist: idna (==3.3)
Requires-Dist: multidict (==6.0.2)
Requires-Dist: multiprocess (==0.70.13)
Requires-Dist: numpy (==1.23.1)
Requires-Dist: packaging (==21.3)
Requires-Dist: pandas (==1.4.3)
Requires-Dist: Pillow (==9.2.0)
Requires-Dist: pyarrow (==8.0.0)
Requires-Dist: pyparsing (==3.0.9)
Requires-Dist: python-dateutil (==2.8.2)
Requires-Dist: pytz (==2022.1)
Requires-Dist: PyYAML (==6.0)
Requires-Dist: regex (==2022.7.9)
Requires-Dist: requests (==2.28.1)
Requires-Dist: resize-right (==0.0.2)
Requires-Dist: responses (==0.18.0)
Requires-Dist: sentencepiece (==0.1.96)
Requires-Dist: six (==1.16.0)
Requires-Dist: tdqm (==0.0.1)
Requires-Dist: tokenizers (==0.12.1)
Requires-Dist: torch (==1.12.0)
Requires-Dist: torchvision (==0.13.0)
Requires-Dist: tqdm (==4.64.0)
Requires-Dist: transformers (==4.20.1)
Requires-Dist: typing-extensions (==4.3.0)
Requires-Dist: urllib3 (==1.26.10)
Requires-Dist: xxhash (==3.0.0)
Requires-Dist: yarl (==1.7.2)
